{
  "kategori": "negara",
  "nama_group": "Chinese Taipei",
  "total_pemain": 2,
  "pemain": [
    {
      "identitas_dasar": {
        "nama_lengkap": "Po-Liang Chen (69690)",
        "nama_panggilan": "Po-Liang Chen (69690)",
        "tanggal_lahir": "1988-08-11",
        "usia": "",
        "tempat_lahir": {
          "kota": "Kaohsiung",
          "negara": "Chinese Taipei"
        },
        "kewarganegaraan": [
          "Chinese Taipei"
        ],
        "tinggi_badan_cm": "180.0",
        "posisi_utama": "Midfield - Central Midfield",
        "kaki_dominan": "right",
        "klub_saat_ini": ""
      },
      "nilai_pasar": {
        "nilai_terkini_eur": "",
        "update_terakhir": ""
      },
      "kontrak": {
        "klub": "",
        "mulai": "",
        "berakhir": ""
      },
      "statistik_performa": {
        "musim": "",
        "main": "",
        "gol": "",
        "assist": ""
      }
    },
    {
      "identitas_dasar": {
        "nama_lengkap": "Yung-Cheng Yuan (802281)",
        "nama_panggilan": "Yung-Cheng Yuan (802281)",
        "tanggal_lahir": "2002-11-12",
        "usia": "",
        "tempat_lahir": {
          "kota": "",
          "negara": ""
        },
        "kewarganegaraan": [
          "Chinese Taipei"
        ],
        "tinggi_badan_cm": "170.0",
        "posisi_utama": "Attack - Right Winger",
        "kaki_dominan": "right",
        "klub_saat_ini": ""
      },
      "nilai_pasar": {
        "nilai_terkini_eur": "",
        "update_terakhir": ""
      },
      "kontrak": {
        "klub": "",
        "mulai": "",
        "berakhir": ""
      },
      "statistik_performa": {
        "musim": "",
        "main": "",
        "gol": "",
        "assist": ""
      }
    }
  ]
}