{
  "kategori": "negara",
  "nama_group": "Cote d'Ivoire  Italy",
  "total_pemain": 26,
  "pemain": [
    {
      "identitas_dasar": {
        "nama_lengkap": "Matteo Mahi (1005598)",
        "nama_panggilan": "Matteo Mahi (1005598)",
        "tanggal_lahir": "2005-02-18",
        "usia": "",
        "tempat_lahir": {
          "kota": "Milano",
          "negara": "Cote d'Ivoire"
        },
        "kewarganegaraan": [
          "Cote d'Ivoire  Italy"
        ],
        "tinggi_badan_cm": "182.0",
        "berat_badan_kg": "",
        "posisi_utama": "Midfield - Central Midfield",
        "posisi_alternatif": "",
        "kaki_dominan": "right",
        "status_pemain": "Aktif",
        "klub_saat_ini": "",
        "nomor_punggung": "",
        "tanggal_gabung": "",
        "kontrak_mulai": "",
        "kontrak_berakhir": "",
        "agen": "",
        "media_sosial": []
      },
      "nilai_pasar": {
        "nilai_terkini_eur": "",
        "update_terakhir": "",
        "riwayat_nilai": [],
        "nilai_tertinggi_eur": ""
      },
      "kontrak": {
        "klub": "",
        "liga": "",
        "mulai": "",
        "berakhir": "",
        "status": "",
        "klausul_rilis": "",
        "gaji_per_musim": ""
      },
      "transfer": [],
      "cedera": [],
      "statistik_performa": {
        "musim": "",
        "main": "",
        "starter": "",
        "substitusi": "",
        "menit_bermain": "",
        "gol": "",
        "assist": "",
        "kuning": "",
        "merah": "",
        "clean_sheet": "",
        "kebobolan": "",
        "rasio_gol_per_menit": "",
        "kontribusi_gol_total": "",
        "per_posisi": {}
      },
      "karier_internasional": {
        "negara": "Cote d'Ivoire  Italy",
        "level": "",
        "caps": "",
        "gol": "",
        "debut": "",
        "turnamen": []
      },
      "prestasi": [],
      "taktikal": {
        "formasi": "",
        "posisi": "",
        "kontribusi_formasi": ""
      },
      "tren_karier": [],
      "sumber_data": {
        "transfermarkt_profile_url": "",
        "data_asal": "transfermarkt",
        "update_terakhir": ""
      }
    },
    {
      "identitas_dasar": {
        "nama_lengkap": "Adama Diakite (120884)",
        "nama_panggilan": "Adama Diakite (120884)",
        "tanggal_lahir": "1993-10-08",
        "usia": "",
        "tempat_lahir": {
          "kota": "Alépé",
          "negara": "Cote d'Ivoire"
        },
        "kewarganegaraan": [
          "Cote d'Ivoire  Italy"
        ],
        "tinggi_badan_cm": "188.0",
        "berat_badan_kg": "",
        "posisi_utama": "Attack - Centre-Forward",
        "posisi_alternatif": "",
        "kaki_dominan": "both",
        "status_pemain": "Aktif",
        "klub_saat_ini": "",
        "nomor_punggung": "",
        "tanggal_gabung": "",
        "kontrak_mulai": "",
        "kontrak_berakhir": "",
        "agen": "",
        "media_sosial": []
      },
      "nilai_pasar": {
        "nilai_terkini_eur": "",
        "update_terakhir": "",
        "riwayat_nilai": [],
        "nilai_tertinggi_eur": ""
      },
      "kontrak": {
        "klub": "",
        "liga": "",
        "mulai": "",
        "berakhir": "",
        "status": "",
        "klausul_rilis": "",
        "gaji_per_musim": ""
      },
      "transfer": [],
      "cedera": [],
      "statistik_performa": {
        "musim": "",
        "main": "",
        "starter": "",
        "substitusi": "",
        "menit_bermain": "",
        "gol": "",
        "assist": "",
        "kuning": "",
        "merah": "",
        "clean_sheet": "",
        "kebobolan": "",
        "rasio_gol_per_menit": "",
        "kontribusi_gol_total": "",
        "per_posisi": {}
      },
      "karier_internasional": {
        "negara": "Cote d'Ivoire  Italy",
        "level": "",
        "caps": "",
        "gol": "",
        "debut": "",
        "turnamen": []
      },
      "prestasi": [],
      "taktikal": {
        "formasi": "",
        "posisi": "",
        "kontribusi_formasi": ""
      },
      "tren_karier": [],
      "sumber_data": {
        "transfermarkt_profile_url": "",
        "data_asal": "transfermarkt",
        "update_terakhir": ""
      }
    },
    {
      "identitas_dasar": {
        "nama_lengkap": "Bala Keita (1177356)",
        "nama_panggilan": "Bala Keita (1177356)",
        "tanggal_lahir": "2007-01-06",
        "usia": "",
        "tempat_lahir": {
          "kota": "",
          "negara": ""
        },
        "kewarganegaraan": [
          "Cote d'Ivoire  Italy"
        ],
        "tinggi_badan_cm": "181.0",
        "berat_badan_kg": "",
        "posisi_utama": "Midfield - Central Midfield",
        "posisi_alternatif": "",
        "kaki_dominan": "right",
        "status_pemain": "Aktif",
        "klub_saat_ini": "",
        "nomor_punggung": "",
        "tanggal_gabung": "",
        "kontrak_mulai": "",
        "kontrak_berakhir": "",
        "agen": "",
        "media_sosial": []
      },
      "nilai_pasar": {
        "nilai_terkini_eur": "",
        "update_terakhir": "",
        "riwayat_nilai": [],
        "nilai_tertinggi_eur": ""
      },
      "kontrak": {
        "klub": "",
        "liga": "",
        "mulai": "",
        "berakhir": "",
        "status": "",
        "klausul_rilis": "",
        "gaji_per_musim": ""
      },
      "transfer": [],
      "cedera": [],
      "statistik_performa": {
        "musim": "",
        "main": "",
        "starter": "",
        "substitusi": "",
        "menit_bermain": "",
        "gol": "",
        "assist": "",
        "kuning": "",
        "merah": "",
        "clean_sheet": "",
        "kebobolan": "",
        "rasio_gol_per_menit": "",
        "kontribusi_gol_total": "",
        "per_posisi": {}
      },
      "karier_internasional": {
        "negara": "Cote d'Ivoire  Italy",
        "level": "",
        "caps": "",
        "gol": "",
        "debut": "",
        "turnamen": []
      },
      "prestasi": [],
      "taktikal": {
        "formasi": "",
        "posisi": "",
        "kontribusi_formasi": ""
      },
      "tren_karier": [],
      "sumber_data": {
        "transfermarkt_profile_url": "",
        "data_asal": "transfermarkt",
        "update_terakhir": ""
      }
    },
    {
      "identitas_dasar": {
        "nama_lengkap": "Aboubakar Bakayoko (163374)",
        "nama_panggilan": "Aboubakar Bakayoko (163374)",
        "tanggal_lahir": "1992-10-14",
        "usia": "",
        "tempat_lahir": {
          "kota": "Brescia",
          "negara": "Cote d'Ivoire"
        },
        "kewarganegaraan": [
          "Cote d'Ivoire  Italy"
        ],
        "tinggi_badan_cm": "188.0",
        "berat_badan_kg": "",
        "posisi_utama": "Defender - Centre-Back",
        "posisi_alternatif": "",
        "kaki_dominan": "left",
        "status_pemain": "Aktif",
        "klub_saat_ini": "",
        "nomor_punggung": "",
        "tanggal_gabung": "",
        "kontrak_mulai": "",
        "kontrak_berakhir": "",
        "agen": "",
        "media_sosial": []
      },
      "nilai_pasar": {
        "nilai_terkini_eur": "",
        "update_terakhir": "",
        "riwayat_nilai": [],
        "nilai_tertinggi_eur": ""
      },
      "kontrak": {
        "klub": "",
        "liga": "",
        "mulai": "",
        "berakhir": "",
        "status": "",
        "klausul_rilis": "",
        "gaji_per_musim": ""
      },
      "transfer": [],
      "cedera": [],
      "statistik_performa": {
        "musim": "",
        "main": "",
        "starter": "",
        "substitusi": "",
        "menit_bermain": "",
        "gol": "",
        "assist": "",
        "kuning": "",
        "merah": "",
        "clean_sheet": "",
        "kebobolan": "",
        "rasio_gol_per_menit": "",
        "kontribusi_gol_total": "",
        "per_posisi": {}
      },
      "karier_internasional": {
        "negara": "Cote d'Ivoire  Italy",
        "level": "",
        "caps": "",
        "gol": "",
        "debut": "",
        "turnamen": []
      },
      "prestasi": [],
      "taktikal": {
        "formasi": "",
        "posisi": "",
        "kontribusi_formasi": ""
      },
      "tren_karier": [],
      "sumber_data": {
        "transfermarkt_profile_url": "",
        "data_asal": "transfermarkt",
        "update_terakhir": ""
      }
    },
    {
      "identitas_dasar": {
        "nama_lengkap": "Cedric Gondo (213854)",
        "nama_panggilan": "Cedric Gondo (213854)",
        "tanggal_lahir": "1996-11-25",
        "usia": "",
        "tempat_lahir": {
          "kota": "Divo",
          "negara": "Cote d'Ivoire"
        },
        "kewarganegaraan": [
          "Cote d'Ivoire  Italy"
        ],
        "tinggi_badan_cm": "187.0",
        "berat_badan_kg": "",
        "posisi_utama": "Attack - Centre-Forward",
        "posisi_alternatif": "",
        "kaki_dominan": "right",
        "status_pemain": "Aktif",
        "klub_saat_ini": "",
        "nomor_punggung": "",
        "tanggal_gabung": "",
        "kontrak_mulai": "",
        "kontrak_berakhir": "",
        "agen": "",
        "media_sosial": []
      },
      "nilai_pasar": {
        "nilai_terkini_eur": "",
        "update_terakhir": "",
        "riwayat_nilai": [],
        "nilai_tertinggi_eur": ""
      },
      "kontrak": {
        "klub": "",
        "liga": "",
        "mulai": "",
        "berakhir": "",
        "status": "",
        "klausul_rilis": "",
        "gaji_per_musim": ""
      },
      "transfer": [],
      "cedera": [],
      "statistik_performa": {
        "musim": "",
        "main": "",
        "starter": "",
        "substitusi": "",
        "menit_bermain": "",
        "gol": "",
        "assist": "",
        "kuning": "",
        "merah": "",
        "clean_sheet": "",
        "kebobolan": "",
        "rasio_gol_per_menit": "",
        "kontribusi_gol_total": "",
        "per_posisi": {}
      },
      "karier_internasional": {
        "negara": "Cote d'Ivoire  Italy",
        "level": "",
        "caps": "",
        "gol": "",
        "debut": "",
        "turnamen": []
      },
      "prestasi": [],
      "taktikal": {
        "formasi": "",
        "posisi": "",
        "kontribusi_formasi": ""
      },
      "tren_karier": [],
      "sumber_data": {
        "transfermarkt_profile_url": "",
        "data_asal": "transfermarkt",
        "update_terakhir": ""
      }
    },
    {
      "identitas_dasar": {
        "nama_lengkap": "Eloge Yao (268590)",
        "nama_panggilan": "Eloge Yao (268590)",
        "tanggal_lahir": "1996-01-20",
        "usia": "",
        "tempat_lahir": {
          "kota": "Akrroukro",
          "negara": "Cote d'Ivoire"
        },
        "kewarganegaraan": [
          "Cote d'Ivoire  Italy"
        ],
        "tinggi_badan_cm": "184.0",
        "berat_badan_kg": "",
        "posisi_utama": "Defender - Right-Back",
        "posisi_alternatif": "",
        "kaki_dominan": "right",
        "status_pemain": "Aktif",
        "klub_saat_ini": "",
        "nomor_punggung": "",
        "tanggal_gabung": "",
        "kontrak_mulai": "",
        "kontrak_berakhir": "",
        "agen": "",
        "media_sosial": []
      },
      "nilai_pasar": {
        "nilai_terkini_eur": "",
        "update_terakhir": "",
        "riwayat_nilai": [],
        "nilai_tertinggi_eur": ""
      },
      "kontrak": {
        "klub": "",
        "liga": "",
        "mulai": "",
        "berakhir": "",
        "status": "",
        "klausul_rilis": "",
        "gaji_per_musim": ""
      },
      "transfer": [],
      "cedera": [],
      "statistik_performa": {
        "musim": "",
        "main": "",
        "starter": "",
        "substitusi": "",
        "menit_bermain": "",
        "gol": "",
        "assist": "",
        "kuning": "",
        "merah": "",
        "clean_sheet": "",
        "kebobolan": "",
        "rasio_gol_per_menit": "",
        "kontribusi_gol_total": "",
        "per_posisi": {}
      },
      "karier_internasional": {
        "negara": "Cote d'Ivoire  Italy",
        "level": "",
        "caps": "",
        "gol": "",
        "debut": "",
        "turnamen": []
      },
      "prestasi": [],
      "taktikal": {
        "formasi": "",
        "posisi": "",
        "kontribusi_formasi": ""
      },
      "tren_karier": [],
      "sumber_data": {
        "transfermarkt_profile_url": "",
        "data_asal": "transfermarkt",
        "update_terakhir": ""
      }
    },
    {
      "identitas_dasar": {
        "nama_lengkap": "Christian Kouamé (337725)",
        "nama_panggilan": "Christian Kouamé (337725)",
        "tanggal_lahir": "1997-12-06",
        "usia": "",
        "tempat_lahir": {
          "kota": "Abidjan",
          "negara": "Cote d'Ivoire"
        },
        "kewarganegaraan": [
          "Cote d'Ivoire  Italy"
        ],
        "tinggi_badan_cm": "185.0",
        "berat_badan_kg": "",
        "posisi_utama": "Attack - Centre-Forward",
        "posisi_alternatif": "",
        "kaki_dominan": "right",
        "status_pemain": "Aktif",
        "klub_saat_ini": "",
        "nomor_punggung": "",
        "tanggal_gabung": "",
        "kontrak_mulai": "",
        "kontrak_berakhir": "",
        "agen": "",
        "media_sosial": []
      },
      "nilai_pasar": {
        "nilai_terkini_eur": "",
        "update_terakhir": "",
        "riwayat_nilai": [],
        "nilai_tertinggi_eur": ""
      },
      "kontrak": {
        "klub": "",
        "liga": "",
        "mulai": "",
        "berakhir": "",
        "status": "",
        "klausul_rilis": "",
        "gaji_per_musim": ""
      },
      "transfer": [],
      "cedera": [],
      "statistik_performa": {
        "musim": "",
        "main": "",
        "starter": "",
        "substitusi": "",
        "menit_bermain": "",
        "gol": "",
        "assist": "",
        "kuning": "",
        "merah": "",
        "clean_sheet": "",
        "kebobolan": "",
        "rasio_gol_per_menit": "",
        "kontribusi_gol_total": "",
        "per_posisi": {}
      },
      "karier_internasional": {
        "negara": "Cote d'Ivoire  Italy",
        "level": "",
        "caps": "",
        "gol": "",
        "debut": "",
        "turnamen": []
      },
      "prestasi": [],
      "taktikal": {
        "formasi": "",
        "posisi": "",
        "kontribusi_formasi": ""
      },
      "tren_karier": [],
      "sumber_data": {
        "transfermarkt_profile_url": "",
        "data_asal": "transfermarkt",
        "update_terakhir": ""
      }
    },
    {
      "identitas_dasar": {
        "nama_lengkap": "Franck Kessié (294808)",
        "nama_panggilan": "Franck Kessié (294808)",
        "tanggal_lahir": "1996-12-19",
        "usia": "",
        "tempat_lahir": {
          "kota": "Ouragahio",
          "negara": "Cote d'Ivoire"
        },
        "kewarganegaraan": [
          "Cote d'Ivoire  Italy"
        ],
        "tinggi_badan_cm": "183.0",
        "berat_badan_kg": "",
        "posisi_utama": "Midfield - Central Midfield",
        "posisi_alternatif": "",
        "kaki_dominan": "right",
        "status_pemain": "Aktif",
        "klub_saat_ini": "",
        "nomor_punggung": "",
        "tanggal_gabung": "",
        "kontrak_mulai": "",
        "kontrak_berakhir": "",
        "agen": "",
        "media_sosial": []
      },
      "nilai_pasar": {
        "nilai_terkini_eur": "",
        "update_terakhir": "",
        "riwayat_nilai": [],
        "nilai_tertinggi_eur": ""
      },
      "kontrak": {
        "klub": "",
        "liga": "",
        "mulai": "",
        "berakhir": "",
        "status": "",
        "klausul_rilis": "",
        "gaji_per_musim": ""
      },
      "transfer": [],
      "cedera": [],
      "statistik_performa": {
        "musim": "",
        "main": "",
        "starter": "",
        "substitusi": "",
        "menit_bermain": "",
        "gol": "",
        "assist": "",
        "kuning": "",
        "merah": "",
        "clean_sheet": "",
        "kebobolan": "",
        "rasio_gol_per_menit": "",
        "kontribusi_gol_total": "",
        "per_posisi": {}
      },
      "karier_internasional": {
        "negara": "Cote d'Ivoire  Italy",
        "level": "",
        "caps": "",
        "gol": "",
        "debut": "",
        "turnamen": []
      },
      "prestasi": [],
      "taktikal": {
        "formasi": "",
        "posisi": "",
        "kontribusi_formasi": ""
      },
      "tren_karier": [],
      "sumber_data": {
        "transfermarkt_profile_url": "",
        "data_asal": "transfermarkt",
        "update_terakhir": ""
      }
    },
    {
      "identitas_dasar": {
        "nama_lengkap": "Emmanuel Achy (392872)",
        "nama_panggilan": "Emmanuel Achy (392872)",
        "tanggal_lahir": "1999-05-05",
        "usia": "",
        "tempat_lahir": {
          "kota": "",
          "negara": ""
        },
        "kewarganegaraan": [
          "Cote d'Ivoire  Italy"
        ],
        "tinggi_badan_cm": "178.0",
        "berat_badan_kg": "",
        "posisi_utama": "Defender - Centre-Back",
        "posisi_alternatif": "",
        "kaki_dominan": "right",
        "status_pemain": "Aktif",
        "klub_saat_ini": "",
        "nomor_punggung": "",
        "tanggal_gabung": "",
        "kontrak_mulai": "",
        "kontrak_berakhir": "",
        "agen": "",
        "media_sosial": []
      },
      "nilai_pasar": {
        "nilai_terkini_eur": "",
        "update_terakhir": "",
        "riwayat_nilai": [],
        "nilai_tertinggi_eur": ""
      },
      "kontrak": {
        "klub": "",
        "liga": "",
        "mulai": "",
        "berakhir": "",
        "status": "",
        "klausul_rilis": "",
        "gaji_per_musim": ""
      },
      "transfer": [],
      "cedera": [],
      "statistik_performa": {
        "musim": "",
        "main": "",
        "starter": "",
        "substitusi": "",
        "menit_bermain": "",
        "gol": "",
        "assist": "",
        "kuning": "",
        "merah": "",
        "clean_sheet": "",
        "kebobolan": "",
        "rasio_gol_per_menit": "",
        "kontribusi_gol_total": "",
        "per_posisi": {}
      },
      "karier_internasional": {
        "negara": "Cote d'Ivoire  Italy",
        "level": "",
        "caps": "",
        "gol": "",
        "debut": "",
        "turnamen": []
      },
      "prestasi": [],
      "taktikal": {
        "formasi": "",
        "posisi": "",
        "kontribusi_formasi": ""
      },
      "tren_karier": [],
      "sumber_data": {
        "transfermarkt_profile_url": "",
        "data_asal": "transfermarkt",
        "update_terakhir": ""
      }
    },
    {
      "identitas_dasar": {
        "nama_lengkap": "Emmanuel Latte Lath (392964)",
        "nama_panggilan": "Emmanuel Latte Lath (392964)",
        "tanggal_lahir": "1999-01-01",
        "usia": "",
        "tempat_lahir": {
          "kota": "Anoumabo Marcory",
          "negara": "Cote d'Ivoire"
        },
        "kewarganegaraan": [
          "Cote d'Ivoire  Italy"
        ],
        "tinggi_badan_cm": "176.0",
        "berat_badan_kg": "",
        "posisi_utama": "Attack - Centre-Forward",
        "posisi_alternatif": "",
        "kaki_dominan": "right",
        "status_pemain": "Aktif",
        "klub_saat_ini": "",
        "nomor_punggung": "",
        "tanggal_gabung": "",
        "kontrak_mulai": "",
        "kontrak_berakhir": "",
        "agen": "",
        "media_sosial": []
      },
      "nilai_pasar": {
        "nilai_terkini_eur": "",
        "update_terakhir": "",
        "riwayat_nilai": [],
        "nilai_tertinggi_eur": ""
      },
      "kontrak": {
        "klub": "",
        "liga": "",
        "mulai": "",
        "berakhir": "",
        "status": "",
        "klausul_rilis": "",
        "gaji_per_musim": ""
      },
      "transfer": [],
      "cedera": [],
      "statistik_performa": {
        "musim": "",
        "main": "",
        "starter": "",
        "substitusi": "",
        "menit_bermain": "",
        "gol": "",
        "assist": "",
        "kuning": "",
        "merah": "",
        "clean_sheet": "",
        "kebobolan": "",
        "rasio_gol_per_menit": "",
        "kontribusi_gol_total": "",
        "per_posisi": {}
      },
      "karier_internasional": {
        "negara": "Cote d'Ivoire  Italy",
        "level": "",
        "caps": "",
        "gol": "",
        "debut": "",
        "turnamen": []
      },
      "prestasi": [],
      "taktikal": {
        "formasi": "",
        "posisi": "",
        "kontribusi_formasi": ""
      },
      "tren_karier": [],
      "sumber_data": {
        "transfermarkt_profile_url": "",
        "data_asal": "transfermarkt",
        "update_terakhir": ""
      }
    },
    {
      "identitas_dasar": {
        "nama_lengkap": "Aziz Malick Sagnini (395727)",
        "nama_panggilan": "Aziz Malick Sagnini (395727)",
        "tanggal_lahir": "1998-12-23",
        "usia": "",
        "tempat_lahir": {
          "kota": "",
          "negara": ""
        },
        "kewarganegaraan": [
          "Cote d'Ivoire  Italy"
        ],
        "tinggi_badan_cm": "0.0",
        "berat_badan_kg": "",
        "posisi_utama": "Attack - Left Winger",
        "posisi_alternatif": "",
        "kaki_dominan": "left",
        "status_pemain": "Aktif",
        "klub_saat_ini": "",
        "nomor_punggung": "",
        "tanggal_gabung": "",
        "kontrak_mulai": "",
        "kontrak_berakhir": "",
        "agen": "",
        "media_sosial": []
      },
      "nilai_pasar": {
        "nilai_terkini_eur": "",
        "update_terakhir": "",
        "riwayat_nilai": [],
        "nilai_tertinggi_eur": ""
      },
      "kontrak": {
        "klub": "",
        "liga": "",
        "mulai": "",
        "berakhir": "",
        "status": "",
        "klausul_rilis": "",
        "gaji_per_musim": ""
      },
      "transfer": [],
      "cedera": [],
      "statistik_performa": {
        "musim": "",
        "main": "",
        "starter": "",
        "substitusi": "",
        "menit_bermain": "",
        "gol": "",
        "assist": "",
        "kuning": "",
        "merah": "",
        "clean_sheet": "",
        "kebobolan": "",
        "rasio_gol_per_menit": "",
        "kontribusi_gol_total": "",
        "per_posisi": {}
      },
      "karier_internasional": {
        "negara": "Cote d'Ivoire  Italy",
        "level": "",
        "caps": "",
        "gol": "",
        "debut": "",
        "turnamen": []
      },
      "prestasi": [],
      "taktikal": {
        "formasi": "",
        "posisi": "",
        "kontribusi_formasi": ""
      },
      "tren_karier": [],
      "sumber_data": {
        "transfermarkt_profile_url": "",
        "data_asal": "transfermarkt",
        "update_terakhir": ""
      }
    },
    {
      "identitas_dasar": {
        "nama_lengkap": "Franck Djoulou (460602)",
        "nama_panggilan": "Franck Djoulou (460602)",
        "tanggal_lahir": "1999-01-01",
        "usia": "",
        "tempat_lahir": {
          "kota": "Okrouyo",
          "negara": "Cote d'Ivoire"
        },
        "kewarganegaraan": [
          "Cote d'Ivoire  Italy"
        ],
        "tinggi_badan_cm": "185.0",
        "berat_badan_kg": "",
        "posisi_utama": "Attack - Left Winger",
        "posisi_alternatif": "",
        "kaki_dominan": "right",
        "status_pemain": "Aktif",
        "klub_saat_ini": "",
        "nomor_punggung": "",
        "tanggal_gabung": "",
        "kontrak_mulai": "",
        "kontrak_berakhir": "",
        "agen": "",
        "media_sosial": []
      },
      "nilai_pasar": {
        "nilai_terkini_eur": "",
        "update_terakhir": "",
        "riwayat_nilai": [],
        "nilai_tertinggi_eur": ""
      },
      "kontrak": {
        "klub": "",
        "liga": "",
        "mulai": "",
        "berakhir": "",
        "status": "",
        "klausul_rilis": "",
        "gaji_per_musim": ""
      },
      "transfer": [],
      "cedera": [],
      "statistik_performa": {
        "musim": "",
        "main": "",
        "starter": "",
        "substitusi": "",
        "menit_bermain": "",
        "gol": "",
        "assist": "",
        "kuning": "",
        "merah": "",
        "clean_sheet": "",
        "kebobolan": "",
        "rasio_gol_per_menit": "",
        "kontribusi_gol_total": "",
        "per_posisi": {}
      },
      "karier_internasional": {
        "negara": "Cote d'Ivoire  Italy",
        "level": "",
        "caps": "",
        "gol": "",
        "debut": "",
        "turnamen": []
      },
      "prestasi": [],
      "taktikal": {
        "formasi": "",
        "posisi": "",
        "kontribusi_formasi": ""
      },
      "tren_karier": [],
      "sumber_data": {
        "transfermarkt_profile_url": "",
        "data_asal": "transfermarkt",
        "update_terakhir": ""
      }
    },
    {
      "identitas_dasar": {
        "nama_lengkap": "Alex Guèhi (457241)",
        "nama_panggilan": "Alex Guèhi (457241)",
        "tanggal_lahir": "2000-01-05",
        "usia": "",
        "tempat_lahir": {
          "kota": "Abidjan",
          "negara": "Cote d'Ivoire"
        },
        "kewarganegaraan": [
          "Cote d'Ivoire  Italy"
        ],
        "tinggi_badan_cm": "0.0",
        "berat_badan_kg": "",
        "posisi_utama": "Attack - Left Winger",
        "posisi_alternatif": "",
        "kaki_dominan": "right",
        "status_pemain": "Aktif",
        "klub_saat_ini": "",
        "nomor_punggung": "",
        "tanggal_gabung": "",
        "kontrak_mulai": "",
        "kontrak_berakhir": "",
        "agen": "",
        "media_sosial": []
      },
      "nilai_pasar": {
        "nilai_terkini_eur": "",
        "update_terakhir": "",
        "riwayat_nilai": [],
        "nilai_tertinggi_eur": ""
      },
      "kontrak": {
        "klub": "",
        "liga": "",
        "mulai": "",
        "berakhir": "",
        "status": "",
        "klausul_rilis": "",
        "gaji_per_musim": ""
      },
      "transfer": [],
      "cedera": [],
      "statistik_performa": {
        "musim": "",
        "main": "",
        "starter": "",
        "substitusi": "",
        "menit_bermain": "",
        "gol": "",
        "assist": "",
        "kuning": "",
        "merah": "",
        "clean_sheet": "",
        "kebobolan": "",
        "rasio_gol_per_menit": "",
        "kontribusi_gol_total": "",
        "per_posisi": {}
      },
      "karier_internasional": {
        "negara": "Cote d'Ivoire  Italy",
        "level": "",
        "caps": "",
        "gol": "",
        "debut": "",
        "turnamen": []
      },
      "prestasi": [],
      "taktikal": {
        "formasi": "",
        "posisi": "",
        "kontribusi_formasi": ""
      },
      "tren_karier": [],
      "sumber_data": {
        "transfermarkt_profile_url": "",
        "data_asal": "transfermarkt",
        "update_terakhir": ""
      }
    },
    {
      "identitas_dasar": {
        "nama_lengkap": "Christian Afri (511002)",
        "nama_panggilan": "Christian Afri (511002)",
        "tanggal_lahir": "2001-01-12",
        "usia": "",
        "tempat_lahir": {
          "kota": "Perugia",
          "negara": "Cote d'Ivoire"
        },
        "kewarganegaraan": [
          "Cote d'Ivoire  Italy"
        ],
        "tinggi_badan_cm": "0.0",
        "berat_badan_kg": "",
        "posisi_utama": "Midfield - Right Midfield",
        "posisi_alternatif": "",
        "kaki_dominan": "right",
        "status_pemain": "Aktif",
        "klub_saat_ini": "",
        "nomor_punggung": "",
        "tanggal_gabung": "",
        "kontrak_mulai": "",
        "kontrak_berakhir": "",
        "agen": "",
        "media_sosial": []
      },
      "nilai_pasar": {
        "nilai_terkini_eur": "",
        "update_terakhir": "",
        "riwayat_nilai": [],
        "nilai_tertinggi_eur": ""
      },
      "kontrak": {
        "klub": "",
        "liga": "",
        "mulai": "",
        "berakhir": "",
        "status": "",
        "klausul_rilis": "",
        "gaji_per_musim": ""
      },
      "transfer": [],
      "cedera": [],
      "statistik_performa": {
        "musim": "",
        "main": "",
        "starter": "",
        "substitusi": "",
        "menit_bermain": "",
        "gol": "",
        "assist": "",
        "kuning": "",
        "merah": "",
        "clean_sheet": "",
        "kebobolan": "",
        "rasio_gol_per_menit": "",
        "kontribusi_gol_total": "",
        "per_posisi": {}
      },
      "karier_internasional": {
        "negara": "Cote d'Ivoire  Italy",
        "level": "",
        "caps": "",
        "gol": "",
        "debut": "",
        "turnamen": []
      },
      "prestasi": [],
      "taktikal": {
        "formasi": "",
        "posisi": "",
        "kontribusi_formasi": ""
      },
      "tren_karier": [],
      "sumber_data": {
        "transfermarkt_profile_url": "",
        "data_asal": "transfermarkt",
        "update_terakhir": ""
      }
    },
    {
      "identitas_dasar": {
        "nama_lengkap": "Amad Diallo (536835)",
        "nama_panggilan": "Amad Diallo (536835)",
        "tanggal_lahir": "2002-07-11",
        "usia": "",
        "tempat_lahir": {
          "kota": "Abidjan",
          "negara": "Cote d'Ivoire"
        },
        "kewarganegaraan": [
          "Cote d'Ivoire  Italy"
        ],
        "tinggi_badan_cm": "173.0",
        "berat_badan_kg": "",
        "posisi_utama": "Attack - Right Winger",
        "posisi_alternatif": "",
        "kaki_dominan": "left",
        "status_pemain": "Aktif",
        "klub_saat_ini": "",
        "nomor_punggung": "",
        "tanggal_gabung": "",
        "kontrak_mulai": "",
        "kontrak_berakhir": "",
        "agen": "",
        "media_sosial": []
      },
      "nilai_pasar": {
        "nilai_terkini_eur": "",
        "update_terakhir": "",
        "riwayat_nilai": [],
        "nilai_tertinggi_eur": ""
      },
      "kontrak": {
        "klub": "",
        "liga": "",
        "mulai": "",
        "berakhir": "",
        "status": "",
        "klausul_rilis": "",
        "gaji_per_musim": ""
      },
      "transfer": [],
      "cedera": [],
      "statistik_performa": {
        "musim": "",
        "main": "",
        "starter": "",
        "substitusi": "",
        "menit_bermain": "",
        "gol": "",
        "assist": "",
        "kuning": "",
        "merah": "",
        "clean_sheet": "",
        "kebobolan": "",
        "rasio_gol_per_menit": "",
        "kontribusi_gol_total": "",
        "per_posisi": {}
      },
      "karier_internasional": {
        "negara": "Cote d'Ivoire  Italy",
        "level": "",
        "caps": "",
        "gol": "",
        "debut": "",
        "turnamen": []
      },
      "prestasi": [],
      "taktikal": {
        "formasi": "",
        "posisi": "",
        "kontribusi_formasi": ""
      },
      "tren_karier": [],
      "sumber_data": {
        "transfermarkt_profile_url": "",
        "data_asal": "transfermarkt",
        "update_terakhir": ""
      }
    },
    {
      "identitas_dasar": {
        "nama_lengkap": "Aboubacar Langone (570717)",
        "nama_panggilan": "Aboubacar Langone (570717)",
        "tanggal_lahir": "2000-07-05",
        "usia": "",
        "tempat_lahir": {
          "kota": "",
          "negara": ""
        },
        "kewarganegaraan": [
          "Cote d'Ivoire  Italy"
        ],
        "tinggi_badan_cm": "185.0",
        "berat_badan_kg": "",
        "posisi_utama": "Midfield - Central Midfield",
        "posisi_alternatif": "",
        "kaki_dominan": "right",
        "status_pemain": "Aktif",
        "klub_saat_ini": "",
        "nomor_punggung": "",
        "tanggal_gabung": "",
        "kontrak_mulai": "",
        "kontrak_berakhir": "",
        "agen": "",
        "media_sosial": []
      },
      "nilai_pasar": {
        "nilai_terkini_eur": "",
        "update_terakhir": "",
        "riwayat_nilai": [],
        "nilai_tertinggi_eur": ""
      },
      "kontrak": {
        "klub": "",
        "liga": "",
        "mulai": "",
        "berakhir": "",
        "status": "",
        "klausul_rilis": "",
        "gaji_per_musim": ""
      },
      "transfer": [],
      "cedera": [],
      "statistik_performa": {
        "musim": "",
        "main": "",
        "starter": "",
        "substitusi": "",
        "menit_bermain": "",
        "gol": "",
        "assist": "",
        "kuning": "",
        "merah": "",
        "clean_sheet": "",
        "kebobolan": "",
        "rasio_gol_per_menit": "",
        "kontribusi_gol_total": "",
        "per_posisi": {}
      },
      "karier_internasional": {
        "negara": "Cote d'Ivoire  Italy",
        "level": "",
        "caps": "",
        "gol": "",
        "debut": "",
        "turnamen": []
      },
      "prestasi": [],
      "taktikal": {
        "formasi": "",
        "posisi": "",
        "kontribusi_formasi": ""
      },
      "tren_karier": [],
      "sumber_data": {
        "transfermarkt_profile_url": "",
        "data_asal": "transfermarkt",
        "update_terakhir": ""
      }
    },
    {
      "identitas_dasar": {
        "nama_lengkap": "Drissa Camara (614742)",
        "nama_panggilan": "Drissa Camara (614742)",
        "tanggal_lahir": "2002-02-18",
        "usia": "",
        "tempat_lahir": {
          "kota": "Abobo",
          "negara": "Cote d'Ivoire"
        },
        "kewarganegaraan": [
          "Cote d'Ivoire  Italy"
        ],
        "tinggi_badan_cm": "179.0",
        "berat_badan_kg": "",
        "posisi_utama": "Midfield - Central Midfield",
        "posisi_alternatif": "",
        "kaki_dominan": "right",
        "status_pemain": "Aktif",
        "klub_saat_ini": "",
        "nomor_punggung": "",
        "tanggal_gabung": "",
        "kontrak_mulai": "",
        "kontrak_berakhir": "",
        "agen": "",
        "media_sosial": []
      },
      "nilai_pasar": {
        "nilai_terkini_eur": "",
        "update_terakhir": "",
        "riwayat_nilai": [],
        "nilai_tertinggi_eur": ""
      },
      "kontrak": {
        "klub": "",
        "liga": "",
        "mulai": "",
        "berakhir": "",
        "status": "",
        "klausul_rilis": "",
        "gaji_per_musim": ""
      },
      "transfer": [],
      "cedera": [],
      "statistik_performa": {
        "musim": "",
        "main": "",
        "starter": "",
        "substitusi": "",
        "menit_bermain": "",
        "gol": "",
        "assist": "",
        "kuning": "",
        "merah": "",
        "clean_sheet": "",
        "kebobolan": "",
        "rasio_gol_per_menit": "",
        "kontribusi_gol_total": "",
        "per_posisi": {}
      },
      "karier_internasional": {
        "negara": "Cote d'Ivoire  Italy",
        "level": "",
        "caps": "",
        "gol": "",
        "debut": "",
        "turnamen": []
      },
      "prestasi": [],
      "taktikal": {
        "formasi": "",
        "posisi": "",
        "kontribusi_formasi": ""
      },
      "tren_karier": [],
      "sumber_data": {
        "transfermarkt_profile_url": "",
        "data_asal": "transfermarkt",
        "update_terakhir": ""
      }
    },
    {
      "identitas_dasar": {
        "nama_lengkap": "",
        "nama_panggilan": "",
        "tanggal_lahir": "2003-10-10",
        "usia": "",
        "tempat_lahir": {
          "kota": "",
          "negara": ""
        },
        "kewarganegaraan": [
          "Cote d'Ivoire  Italy"
        ],
        "tinggi_badan_cm": "0.0",
        "berat_badan_kg": "",
        "posisi_utama": "Attack - Centre-Forward",
        "posisi_alternatif": "",
        "kaki_dominan": "",
        "status_pemain": "Aktif",
        "klub_saat_ini": "",
        "nomor_punggung": "",
        "tanggal_gabung": "",
        "kontrak_mulai": "",
        "kontrak_berakhir": "",
        "agen": "",
        "media_sosial": []
      },
      "nilai_pasar": {
        "nilai_terkini_eur": "",
        "update_terakhir": "",
        "riwayat_nilai": [],
        "nilai_tertinggi_eur": ""
      },
      "kontrak": {
        "klub": "",
        "liga": "",
        "mulai": "",
        "berakhir": "",
        "status": "",
        "klausul_rilis": "",
        "gaji_per_musim": ""
      },
      "transfer": [],
      "cedera": [],
      "statistik_performa": {
        "musim": "",
        "main": "",
        "starter": "",
        "substitusi": "",
        "menit_bermain": "",
        "gol": "",
        "assist": "",
        "kuning": "",
        "merah": "",
        "clean_sheet": "",
        "kebobolan": "",
        "rasio_gol_per_menit": "",
        "kontribusi_gol_total": "",
        "per_posisi": {}
      },
      "karier_internasional": {
        "negara": "Cote d'Ivoire  Italy",
        "level": "",
        "caps": "",
        "gol": "",
        "debut": "",
        "turnamen": []
      },
      "prestasi": [],
      "taktikal": {
        "formasi": "",
        "posisi": "",
        "kontribusi_formasi": ""
      },
      "tren_karier": [],
      "sumber_data": {
        "transfermarkt_profile_url": "",
        "data_asal": "transfermarkt",
        "update_terakhir": ""
      }
    },
    {
      "identitas_dasar": {
        "nama_lengkap": "Kevin Koffi (61758)",
        "nama_panggilan": "Kevin Koffi (61758)",
        "tanggal_lahir": "1986-06-25",
        "usia": "",
        "tempat_lahir": {
          "kota": "Aboisso",
          "negara": "Cote d'Ivoire"
        },
        "kewarganegaraan": [
          "Cote d'Ivoire  Italy"
        ],
        "tinggi_badan_cm": "181.0",
        "berat_badan_kg": "",
        "posisi_utama": "Attack - Centre-Forward",
        "posisi_alternatif": "",
        "kaki_dominan": "right",
        "status_pemain": "Aktif",
        "klub_saat_ini": "",
        "nomor_punggung": "",
        "tanggal_gabung": "",
        "kontrak_mulai": "",
        "kontrak_berakhir": "",
        "agen": "",
        "media_sosial": []
      },
      "nilai_pasar": {
        "nilai_terkini_eur": "",
        "update_terakhir": "",
        "riwayat_nilai": [],
        "nilai_tertinggi_eur": ""
      },
      "kontrak": {
        "klub": "",
        "liga": "",
        "mulai": "",
        "berakhir": "",
        "status": "",
        "klausul_rilis": "",
        "gaji_per_musim": ""
      },
      "transfer": [],
      "cedera": [],
      "statistik_performa": {
        "musim": "",
        "main": "",
        "starter": "",
        "substitusi": "",
        "menit_bermain": "",
        "gol": "",
        "assist": "",
        "kuning": "",
        "merah": "",
        "clean_sheet": "",
        "kebobolan": "",
        "rasio_gol_per_menit": "",
        "kontribusi_gol_total": "",
        "per_posisi": {}
      },
      "karier_internasional": {
        "negara": "Cote d'Ivoire  Italy",
        "level": "",
        "caps": "",
        "gol": "",
        "debut": "",
        "turnamen": []
      },
      "prestasi": [],
      "taktikal": {
        "formasi": "",
        "posisi": "",
        "kontribusi_formasi": ""
      },
      "tren_karier": [],
      "sumber_data": {
        "transfermarkt_profile_url": "",
        "data_asal": "transfermarkt",
        "update_terakhir": ""
      }
    },
    {
      "identitas_dasar": {
        "nama_lengkap": "Christian Manfredini (5850)",
        "nama_panggilan": "Christian Manfredini (5850)",
        "tanggal_lahir": "1975-05-01",
        "usia": "",
        "tempat_lahir": {
          "kota": "Port-Bouët",
          "negara": "Cote d'Ivoire"
        },
        "kewarganegaraan": [
          "Cote d'Ivoire  Italy"
        ],
        "tinggi_badan_cm": "180.0",
        "berat_badan_kg": "",
        "posisi_utama": "Attack - Left Winger",
        "posisi_alternatif": "",
        "kaki_dominan": "left",
        "status_pemain": "Aktif",
        "klub_saat_ini": "",
        "nomor_punggung": "",
        "tanggal_gabung": "",
        "kontrak_mulai": "",
        "kontrak_berakhir": "",
        "agen": "",
        "media_sosial": []
      },
      "nilai_pasar": {
        "nilai_terkini_eur": "",
        "update_terakhir": "",
        "riwayat_nilai": [],
        "nilai_tertinggi_eur": ""
      },
      "kontrak": {
        "klub": "",
        "liga": "",
        "mulai": "",
        "berakhir": "",
        "status": "",
        "klausul_rilis": "",
        "gaji_per_musim": ""
      },
      "transfer": [],
      "cedera": [],
      "statistik_performa": {
        "musim": "",
        "main": "",
        "starter": "",
        "substitusi": "",
        "menit_bermain": "",
        "gol": "",
        "assist": "",
        "kuning": "",
        "merah": "",
        "clean_sheet": "",
        "kebobolan": "",
        "rasio_gol_per_menit": "",
        "kontribusi_gol_total": "",
        "per_posisi": {}
      },
      "karier_internasional": {
        "negara": "Cote d'Ivoire  Italy",
        "level": "",
        "caps": "",
        "gol": "",
        "debut": "",
        "turnamen": []
      },
      "prestasi": [],
      "taktikal": {
        "formasi": "",
        "posisi": "",
        "kontribusi_formasi": ""
      },
      "tren_karier": [],
      "sumber_data": {
        "transfermarkt_profile_url": "",
        "data_asal": "transfermarkt",
        "update_terakhir": ""
      }
    },
    {
      "identitas_dasar": {
        "nama_lengkap": "Abdoulaye Bamba (62351)",
        "nama_panggilan": "Abdoulaye Bamba (62351)",
        "tanggal_lahir": "1990-04-25",
        "usia": "",
        "tempat_lahir": {
          "kota": "Abidjan",
          "negara": "Cote d'Ivoire"
        },
        "kewarganegaraan": [
          "Cote d'Ivoire  Italy"
        ],
        "tinggi_badan_cm": "182.0",
        "berat_badan_kg": "",
        "posisi_utama": "Defender - Centre-Back",
        "posisi_alternatif": "",
        "kaki_dominan": "right",
        "status_pemain": "Aktif",
        "klub_saat_ini": "",
        "nomor_punggung": "",
        "tanggal_gabung": "",
        "kontrak_mulai": "",
        "kontrak_berakhir": "",
        "agen": "",
        "media_sosial": []
      },
      "nilai_pasar": {
        "nilai_terkini_eur": "",
        "update_terakhir": "",
        "riwayat_nilai": [],
        "nilai_tertinggi_eur": ""
      },
      "kontrak": {
        "klub": "",
        "liga": "",
        "mulai": "",
        "berakhir": "",
        "status": "",
        "klausul_rilis": "",
        "gaji_per_musim": ""
      },
      "transfer": [],
      "cedera": [],
      "statistik_performa": {
        "musim": "",
        "main": "",
        "starter": "",
        "substitusi": "",
        "menit_bermain": "",
        "gol": "",
        "assist": "",
        "kuning": "",
        "merah": "",
        "clean_sheet": "",
        "kebobolan": "",
        "rasio_gol_per_menit": "",
        "kontribusi_gol_total": "",
        "per_posisi": {}
      },
      "karier_internasional": {
        "negara": "Cote d'Ivoire  Italy",
        "level": "",
        "caps": "",
        "gol": "",
        "debut": "",
        "turnamen": []
      },
      "prestasi": [],
      "taktikal": {
        "formasi": "",
        "posisi": "",
        "kontribusi_formasi": ""
      },
      "tren_karier": [],
      "sumber_data": {
        "transfermarkt_profile_url": "",
        "data_asal": "transfermarkt",
        "update_terakhir": ""
      }
    },
    {
      "identitas_dasar": {
        "nama_lengkap": "Cedrick Koffi (703226)",
        "nama_panggilan": "Cedrick Koffi (703226)",
        "tanggal_lahir": "2004-07-23",
        "usia": "",
        "tempat_lahir": {
          "kota": "Yamoussoukro",
          "negara": "Cote d'Ivoire"
        },
        "kewarganegaraan": [
          "Cote d'Ivoire  Italy"
        ],
        "tinggi_badan_cm": "0.0",
        "berat_badan_kg": "",
        "posisi_utama": "Attack - Left Winger",
        "posisi_alternatif": "",
        "kaki_dominan": "right",
        "status_pemain": "Aktif",
        "klub_saat_ini": "",
        "nomor_punggung": "",
        "tanggal_gabung": "",
        "kontrak_mulai": "",
        "kontrak_berakhir": "",
        "agen": "",
        "media_sosial": []
      },
      "nilai_pasar": {
        "nilai_terkini_eur": "",
        "update_terakhir": "",
        "riwayat_nilai": [],
        "nilai_tertinggi_eur": ""
      },
      "kontrak": {
        "klub": "",
        "liga": "",
        "mulai": "",
        "berakhir": "",
        "status": "",
        "klausul_rilis": "",
        "gaji_per_musim": ""
      },
      "transfer": [],
      "cedera": [],
      "statistik_performa": {
        "musim": "",
        "main": "",
        "starter": "",
        "substitusi": "",
        "menit_bermain": "",
        "gol": "",
        "assist": "",
        "kuning": "",
        "merah": "",
        "clean_sheet": "",
        "kebobolan": "",
        "rasio_gol_per_menit": "",
        "kontribusi_gol_total": "",
        "per_posisi": {}
      },
      "karier_internasional": {
        "negara": "Cote d'Ivoire  Italy",
        "level": "",
        "caps": "",
        "gol": "",
        "debut": "",
        "turnamen": []
      },
      "prestasi": [],
      "taktikal": {
        "formasi": "",
        "posisi": "",
        "kontribusi_formasi": ""
      },
      "tren_karier": [],
      "sumber_data": {
        "transfermarkt_profile_url": "",
        "data_asal": "transfermarkt",
        "update_terakhir": ""
      }
    },
    {
      "identitas_dasar": {
        "nama_lengkap": "Landry Boni (709511)",
        "nama_panggilan": "Landry Boni (709511)",
        "tanggal_lahir": "2004-02-19",
        "usia": "",
        "tempat_lahir": {
          "kota": "Abidjan",
          "negara": "Cote d'Ivoire"
        },
        "kewarganegaraan": [
          "Cote d'Ivoire  Italy"
        ],
        "tinggi_badan_cm": "0.0",
        "berat_badan_kg": "",
        "posisi_utama": "Midfield - Attacking Midfield",
        "posisi_alternatif": "",
        "kaki_dominan": "right",
        "status_pemain": "Aktif",
        "klub_saat_ini": "",
        "nomor_punggung": "",
        "tanggal_gabung": "",
        "kontrak_mulai": "",
        "kontrak_berakhir": "",
        "agen": "",
        "media_sosial": []
      },
      "nilai_pasar": {
        "nilai_terkini_eur": "",
        "update_terakhir": "",
        "riwayat_nilai": [],
        "nilai_tertinggi_eur": ""
      },
      "kontrak": {
        "klub": "",
        "liga": "",
        "mulai": "",
        "berakhir": "",
        "status": "",
        "klausul_rilis": "",
        "gaji_per_musim": ""
      },
      "transfer": [],
      "cedera": [],
      "statistik_performa": {
        "musim": "",
        "main": "",
        "starter": "",
        "substitusi": "",
        "menit_bermain": "",
        "gol": "",
        "assist": "",
        "kuning": "",
        "merah": "",
        "clean_sheet": "",
        "kebobolan": "",
        "rasio_gol_per_menit": "",
        "kontribusi_gol_total": "",
        "per_posisi": {}
      },
      "karier_internasional": {
        "negara": "Cote d'Ivoire  Italy",
        "level": "",
        "caps": "",
        "gol": "",
        "debut": "",
        "turnamen": []
      },
      "prestasi": [],
      "taktikal": {
        "formasi": "",
        "posisi": "",
        "kontribusi_formasi": ""
      },
      "tren_karier": [],
      "sumber_data": {
        "transfermarkt_profile_url": "",
        "data_asal": "transfermarkt",
        "update_terakhir": ""
      }
    },
    {
      "identitas_dasar": {
        "nama_lengkap": "Yannick Melseaux (821198)",
        "nama_panggilan": "Yannick Melseaux (821198)",
        "tanggal_lahir": "2004-01-16",
        "usia": "",
        "tempat_lahir": {
          "kota": "",
          "negara": ""
        },
        "kewarganegaraan": [
          "Cote d'Ivoire  Italy"
        ],
        "tinggi_badan_cm": "0.0",
        "berat_badan_kg": "",
        "posisi_utama": "Defender - Right-Back",
        "posisi_alternatif": "",
        "kaki_dominan": "",
        "status_pemain": "Aktif",
        "klub_saat_ini": "",
        "nomor_punggung": "",
        "tanggal_gabung": "",
        "kontrak_mulai": "",
        "kontrak_berakhir": "",
        "agen": "",
        "media_sosial": []
      },
      "nilai_pasar": {
        "nilai_terkini_eur": "",
        "update_terakhir": "",
        "riwayat_nilai": [],
        "nilai_tertinggi_eur": ""
      },
      "kontrak": {
        "klub": "",
        "liga": "",
        "mulai": "",
        "berakhir": "",
        "status": "",
        "klausul_rilis": "",
        "gaji_per_musim": ""
      },
      "transfer": [],
      "cedera": [],
      "statistik_performa": {
        "musim": "",
        "main": "",
        "starter": "",
        "substitusi": "",
        "menit_bermain": "",
        "gol": "",
        "assist": "",
        "kuning": "",
        "merah": "",
        "clean_sheet": "",
        "kebobolan": "",
        "rasio_gol_per_menit": "",
        "kontribusi_gol_total": "",
        "per_posisi": {}
      },
      "karier_internasional": {
        "negara": "Cote d'Ivoire  Italy",
        "level": "",
        "caps": "",
        "gol": "",
        "debut": "",
        "turnamen": []
      },
      "prestasi": [],
      "taktikal": {
        "formasi": "",
        "posisi": "",
        "kontribusi_formasi": ""
      },
      "tren_karier": [],
      "sumber_data": {
        "transfermarkt_profile_url": "",
        "data_asal": "transfermarkt",
        "update_terakhir": ""
      }
    },
    {
      "identitas_dasar": {
        "nama_lengkap": "Sekou Koné (909230)",
        "nama_panggilan": "Sekou Koné (909230)",
        "tanggal_lahir": "2000-12-31",
        "usia": "",
        "tempat_lahir": {
          "kota": "",
          "negara": ""
        },
        "kewarganegaraan": [
          "Cote d'Ivoire  Italy"
        ],
        "tinggi_badan_cm": "182.0",
        "berat_badan_kg": "",
        "posisi_utama": "Attack",
        "posisi_alternatif": "",
        "kaki_dominan": "",
        "status_pemain": "Aktif",
        "klub_saat_ini": "",
        "nomor_punggung": "",
        "tanggal_gabung": "",
        "kontrak_mulai": "",
        "kontrak_berakhir": "",
        "agen": "",
        "media_sosial": []
      },
      "nilai_pasar": {
        "nilai_terkini_eur": "",
        "update_terakhir": "",
        "riwayat_nilai": [],
        "nilai_tertinggi_eur": ""
      },
      "kontrak": {
        "klub": "",
        "liga": "",
        "mulai": "",
        "berakhir": "",
        "status": "",
        "klausul_rilis": "",
        "gaji_per_musim": ""
      },
      "transfer": [],
      "cedera": [],
      "statistik_performa": {
        "musim": "",
        "main": "",
        "starter": "",
        "substitusi": "",
        "menit_bermain": "",
        "gol": "",
        "assist": "",
        "kuning": "",
        "merah": "",
        "clean_sheet": "",
        "kebobolan": "",
        "rasio_gol_per_menit": "",
        "kontribusi_gol_total": "",
        "per_posisi": {}
      },
      "karier_internasional": {
        "negara": "Cote d'Ivoire  Italy",
        "level": "",
        "caps": "",
        "gol": "",
        "debut": "",
        "turnamen": []
      },
      "prestasi": [],
      "taktikal": {
        "formasi": "",
        "posisi": "",
        "kontribusi_formasi": ""
      },
      "tren_karier": [],
      "sumber_data": {
        "transfermarkt_profile_url": "",
        "data_asal": "transfermarkt",
        "update_terakhir": ""
      }
    },
    {
      "identitas_dasar": {
        "nama_lengkap": "Larsson Coulibaly (867545)",
        "nama_panggilan": "Larsson Coulibaly (867545)",
        "tanggal_lahir": "2003-04-17",
        "usia": "",
        "tempat_lahir": {
          "kota": "Yopougon",
          "negara": "Cote d'Ivoire"
        },
        "kewarganegaraan": [
          "Cote d'Ivoire  Italy"
        ],
        "tinggi_badan_cm": "180.0",
        "berat_badan_kg": "",
        "posisi_utama": "Midfield - Central Midfield",
        "posisi_alternatif": "",
        "kaki_dominan": "right",
        "status_pemain": "Aktif",
        "klub_saat_ini": "",
        "nomor_punggung": "",
        "tanggal_gabung": "",
        "kontrak_mulai": "",
        "kontrak_berakhir": "",
        "agen": "",
        "media_sosial": []
      },
      "nilai_pasar": {
        "nilai_terkini_eur": "",
        "update_terakhir": "",
        "riwayat_nilai": [],
        "nilai_tertinggi_eur": ""
      },
      "kontrak": {
        "klub": "",
        "liga": "",
        "mulai": "",
        "berakhir": "",
        "status": "",
        "klausul_rilis": "",
        "gaji_per_musim": ""
      },
      "transfer": [],
      "cedera": [],
      "statistik_performa": {
        "musim": "",
        "main": "",
        "starter": "",
        "substitusi": "",
        "menit_bermain": "",
        "gol": "",
        "assist": "",
        "kuning": "",
        "merah": "",
        "clean_sheet": "",
        "kebobolan": "",
        "rasio_gol_per_menit": "",
        "kontribusi_gol_total": "",
        "per_posisi": {}
      },
      "karier_internasional": {
        "negara": "Cote d'Ivoire  Italy",
        "level": "",
        "caps": "",
        "gol": "",
        "debut": "",
        "turnamen": []
      },
      "prestasi": [],
      "taktikal": {
        "formasi": "",
        "posisi": "",
        "kontribusi_formasi": ""
      },
      "tren_karier": [],
      "sumber_data": {
        "transfermarkt_profile_url": "",
        "data_asal": "transfermarkt",
        "update_terakhir": ""
      }
    }
  ]
}