{
  "kategori": "negara",
  "nama_group": "Hungary  Slovakia",
  "total_pemain": 4,
  "pemain": [
    {
      "identitas_dasar": {
        "nama_lengkap": "Péter Benkő (1030944)",
        "nama_panggilan": "Péter Benkő (1030944)",
        "tanggal_lahir": "2003-01-30",
        "usia": "",
        "tempat_lahir": {
          "kota": "Rimavská Sobota",
          "negara": "Hungary"
        },
        "kewarganegaraan": [
          "Hungary  Slovakia"
        ],
        "tinggi_badan_cm": "174.0",
        "posisi_utama": "Attack - Left Winger",
        "kaki_dominan": "left",
        "klub_saat_ini": ""
      },
      "nilai_pasar": {
        "nilai_terkini_eur": "",
        "update_terakhir": ""
      },
      "kontrak": {
        "klub": "",
        "mulai": "",
        "berakhir": ""
      },
      "statistik_performa": {
        "musim": "",
        "main": "",
        "gol": "",
        "assist": ""
      }
    },
    {
      "identitas_dasar": {
        "nama_lengkap": "Sinan Medgyes (229716)",
        "nama_panggilan": "Sinan Medgyes (229716)",
        "tanggal_lahir": "1993-06-30",
        "usia": "",
        "tempat_lahir": {
          "kota": "Dunajská Streda",
          "negara": "Hungary"
        },
        "kewarganegaraan": [
          "Hungary  Slovakia"
        ],
        "tinggi_badan_cm": "185.0",
        "posisi_utama": "Defender - Left-Back",
        "kaki_dominan": "left",
        "klub_saat_ini": ""
      },
      "nilai_pasar": {
        "nilai_terkini_eur": "",
        "update_terakhir": ""
      },
      "kontrak": {
        "klub": "",
        "mulai": "",
        "berakhir": ""
      },
      "statistik_performa": {
        "musim": "",
        "main": "",
        "gol": "",
        "assist": ""
      }
    },
    {
      "identitas_dasar": {
        "nama_lengkap": "Gábor Boros (300835)",
        "nama_panggilan": "Gábor Boros (300835)",
        "tanggal_lahir": "1997-09-26",
        "usia": "",
        "tempat_lahir": {
          "kota": "Rimavská Sobota",
          "negara": "Hungary"
        },
        "kewarganegaraan": [
          "Hungary  Slovakia"
        ],
        "tinggi_badan_cm": "183.0",
        "posisi_utama": "Attack - Centre-Forward",
        "kaki_dominan": "right",
        "klub_saat_ini": ""
      },
      "nilai_pasar": {
        "nilai_terkini_eur": "",
        "update_terakhir": ""
      },
      "kontrak": {
        "klub": "",
        "mulai": "",
        "berakhir": ""
      },
      "statistik_performa": {
        "musim": "",
        "main": "",
        "gol": "",
        "assist": ""
      }
    },
    {
      "identitas_dasar": {
        "nama_lengkap": "Rostislav Prokop (488892)",
        "nama_panggilan": "Rostislav Prokop (488892)",
        "tanggal_lahir": "1996-03-19",
        "usia": "",
        "tempat_lahir": {
          "kota": "Dunajská Streda",
          "negara": "Hungary"
        },
        "kewarganegaraan": [
          "Hungary  Slovakia"
        ],
        "tinggi_badan_cm": "0.0",
        "posisi_utama": "Goalkeeper",
        "kaki_dominan": "right",
        "klub_saat_ini": ""
      },
      "nilai_pasar": {
        "nilai_terkini_eur": "",
        "update_terakhir": ""
      },
      "kontrak": {
        "klub": "",
        "mulai": "",
        "berakhir": ""
      },
      "statistik_performa": {
        "musim": "",
        "main": "",
        "gol": "",
        "assist": ""
      }
    }
  ]
}