{
  "kategori": "negara",
  "nama_group": "Italy  Spain",
  "total_pemain": 8,
  "pemain": [
    {
      "identitas_dasar": {
        "nama_lengkap": "Pablo Mangiaracina-Lopez (1059208)",
        "nama_panggilan": "Pablo Mangiaracina-Lopez (1059208)",
        "tanggal_lahir": "2006-04-10",
        "usia": "",
        "tempat_lahir": {
          "kota": "Padova",
          "negara": "Italy"
        },
        "kewarganegaraan": [
          "Italy  Spain"
        ],
        "tinggi_badan_cm": "189.0",
        "posisi_utama": "Goalkeeper",
        "kaki_dominan": "",
        "klub_saat_ini": ""
      },
      "nilai_pasar": {
        "nilai_terkini_eur": "",
        "update_terakhir": ""
      },
      "kontrak": {
        "klub": "",
        "mulai": "",
        "berakhir": ""
      },
      "statistik_performa": {
        "musim": "",
        "main": "",
        "gol": "",
        "assist": ""
      }
    },
    {
      "identitas_dasar": {
        "nama_lengkap": "Sandro Villani (11294)",
        "nama_panggilan": "Sandro Villani (11294)",
        "tanggal_lahir": "1982-09-13",
        "usia": "",
        "tempat_lahir": {
          "kota": "",
          "negara": ""
        },
        "kewarganegaraan": [
          "Italy  Spain"
        ],
        "tinggi_badan_cm": "0.0",
        "posisi_utama": "Midfield - Attacking Midfield",
        "kaki_dominan": "N/A",
        "klub_saat_ini": ""
      },
      "nilai_pasar": {
        "nilai_terkini_eur": "",
        "update_terakhir": ""
      },
      "kontrak": {
        "klub": "",
        "mulai": "",
        "berakhir": ""
      },
      "statistik_performa": {
        "musim": "",
        "main": "",
        "gol": "",
        "assist": ""
      }
    },
    {
      "identitas_dasar": {
        "nama_lengkap": "Andrés Llamas (265087)",
        "nama_panggilan": "Andrés Llamas (265087)",
        "tanggal_lahir": "1998-05-07",
        "usia": "",
        "tempat_lahir": {
          "kota": "Milano",
          "negara": "Italy"
        },
        "kewarganegaraan": [
          "Italy  Spain"
        ],
        "tinggi_badan_cm": "185.0",
        "posisi_utama": "Defender - Left-Back",
        "kaki_dominan": "left",
        "klub_saat_ini": ""
      },
      "nilai_pasar": {
        "nilai_terkini_eur": "",
        "update_terakhir": ""
      },
      "kontrak": {
        "klub": "",
        "mulai": "",
        "berakhir": ""
      },
      "statistik_performa": {
        "musim": "",
        "main": "",
        "gol": "",
        "assist": ""
      }
    },
    {
      "identitas_dasar": {
        "nama_lengkap": "Manél Minicucci (239593)",
        "nama_panggilan": "Manél Minicucci (239593)",
        "tanggal_lahir": "1995-05-13",
        "usia": "",
        "tempat_lahir": {
          "kota": "Roma",
          "negara": "Italy"
        },
        "kewarganegaraan": [
          "Italy  Spain"
        ],
        "tinggi_badan_cm": "180.0",
        "posisi_utama": "Attack - Right Winger",
        "kaki_dominan": "left",
        "klub_saat_ini": ""
      },
      "nilai_pasar": {
        "nilai_terkini_eur": "",
        "update_terakhir": ""
      },
      "kontrak": {
        "klub": "",
        "mulai": "",
        "berakhir": ""
      },
      "statistik_performa": {
        "musim": "",
        "main": "",
        "gol": "",
        "assist": ""
      }
    },
    {
      "identitas_dasar": {
        "nama_lengkap": "Jaime Martínez (397749)",
        "nama_panggilan": "Jaime Martínez (397749)",
        "tanggal_lahir": "1981-09-18",
        "usia": "",
        "tempat_lahir": {
          "kota": "Madrid",
          "negara": "Italy"
        },
        "kewarganegaraan": [
          "Italy  Spain"
        ],
        "tinggi_badan_cm": "188.0",
        "posisi_utama": "Attack - Centre-Forward",
        "kaki_dominan": "right",
        "klub_saat_ini": ""
      },
      "nilai_pasar": {
        "nilai_terkini_eur": "",
        "update_terakhir": ""
      },
      "kontrak": {
        "klub": "",
        "mulai": "",
        "berakhir": ""
      },
      "statistik_performa": {
        "musim": "",
        "main": "",
        "gol": "",
        "assist": ""
      }
    },
    {
      "identitas_dasar": {
        "nama_lengkap": "Francesco Guidoni (673985)",
        "nama_panggilan": "Francesco Guidoni (673985)",
        "tanggal_lahir": "2002-02-05",
        "usia": "",
        "tempat_lahir": {
          "kota": "Marbella",
          "negara": "Italy"
        },
        "kewarganegaraan": [
          "Italy  Spain"
        ],
        "tinggi_badan_cm": "172.0",
        "posisi_utama": "Attack - Left Winger",
        "kaki_dominan": "right",
        "klub_saat_ini": ""
      },
      "nilai_pasar": {
        "nilai_terkini_eur": "",
        "update_terakhir": ""
      },
      "kontrak": {
        "klub": "",
        "mulai": "",
        "berakhir": ""
      },
      "statistik_performa": {
        "musim": "",
        "main": "",
        "gol": "",
        "assist": ""
      }
    },
    {
      "identitas_dasar": {
        "nama_lengkap": "Iker Schiavella (705349)",
        "nama_panggilan": "Iker Schiavella (705349)",
        "tanggal_lahir": "2003-01-25",
        "usia": "",
        "tempat_lahir": {
          "kota": "",
          "negara": ""
        },
        "kewarganegaraan": [
          "Italy  Spain"
        ],
        "tinggi_badan_cm": "0.0",
        "posisi_utama": "Midfield - Central Midfield",
        "kaki_dominan": "",
        "klub_saat_ini": ""
      },
      "nilai_pasar": {
        "nilai_terkini_eur": "",
        "update_terakhir": ""
      },
      "kontrak": {
        "klub": "",
        "mulai": "",
        "berakhir": ""
      },
      "statistik_performa": {
        "musim": "",
        "main": "",
        "gol": "",
        "assist": ""
      }
    },
    {
      "identitas_dasar": {
        "nama_lengkap": "Pablo Vitali (811397)",
        "nama_panggilan": "Pablo Vitali (811397)",
        "tanggal_lahir": "2002-07-07",
        "usia": "",
        "tempat_lahir": {
          "kota": "Roma",
          "negara": "Italy"
        },
        "kewarganegaraan": [
          "Italy  Spain"
        ],
        "tinggi_badan_cm": "186.0",
        "posisi_utama": "Attack - Right Winger",
        "kaki_dominan": "left",
        "klub_saat_ini": ""
      },
      "nilai_pasar": {
        "nilai_terkini_eur": "",
        "update_terakhir": ""
      },
      "kontrak": {
        "klub": "",
        "mulai": "",
        "berakhir": ""
      },
      "statistik_performa": {
        "musim": "",
        "main": "",
        "gol": "",
        "assist": ""
      }
    }
  ]
}