{
  "player_id": "1072473",
  "player_slug": "bilal-bouhadjar",
  "player_name": "Bilal Bouhadjar (1072473)",
  "player_image_url": "https://img.a.transfermarkt.technology/portrait/header/default.jpg",
  "name_in_home_country": "",
  "date_of_birth": "2006-07-10",
  "place_of_birth": "",
  "country_of_birth": "",
  "height": "0.0",
  "citizenship": "France  Algeria",
  "is_eu": "True",
  "position": "Attack",
  "main_position": "Attack",
  "foot": "",
  "current_club_id": "56614",
  "current_club_name": "AS Béziers B",
  "joined": "2023-07-01",
  "contract_expires": "",
  "outfitter": "",
  "social_media_url": "",
  "player_agent_id": "",
  "player_agent_name": "",
  "contract_option": "",
  "date_of_last_contract_extension": "",
  "on_loan_from_club_id": "",
  "on_loan_from_club_name": "",
  "contract_there_expires": "",
  "second_club_url": "/as-beziers/startseite/verein/10867",
  "second_club_name": "AS Béziers",
  "third_club_url": "",
  "third_club_name": "",
  "fourth_club_url": "",
  "fourth_club_name": "",
  "date_of_death": ""
}