{
  "player_id": "113052",
  "player_slug": "leandro-kappel",
  "player_name": "Leandro Kappel (113052)",
  "player_image_url": "https://img.a.transfermarkt.technology/portrait/header/113052-1636936003.jpeg",
  "name_in_home_country": "Leandro Deyrinio Kappel",
  "date_of_birth": "1989-11-14",
  "place_of_birth": "Amsterdam",
  "country_of_birth": "Suriname",
  "height": "183.0",
  "citizenship": "Suriname  Netherlands",
  "is_eu": "True",
  "position": "Attack - Right Winger",
  "main_position": "Attack",
  "foot": "left",
  "current_club_id": "515",
  "current_club_name": "Without Club",
  "joined": "2025-07-01",
  "contract_expires": "",
  "outfitter": "",
  "social_media_url": "http://www.instagram.com/leandro.kappel/",
  "player_agent_id": "2992",
  "player_agent_name": "The Libra Enterprise",
  "contract_option": "",
  "date_of_last_contract_extension": "",
  "on_loan_from_club_id": "",
  "on_loan_from_club_name": "",
  "contract_there_expires": "",
  "second_club_url": "",
  "second_club_name": "",
  "third_club_url": "",
  "third_club_name": "",
  "fourth_club_url": "",
  "fourth_club_name": "",
  "date_of_death": ""
}