{
  "player_id": "126516",
  "player_slug": "antonio-luna",
  "player_name": "Antonio Luna (126516)",
  "player_image_url": "https://img.a.transfermarkt.technology/portrait/header/126516-1447246479.jpg",
  "name_in_home_country": "Antonio Manuel Luna Rodríguez",
  "date_of_birth": "1991-03-17",
  "place_of_birth": "Son Servera",
  "country_of_birth": "Spain",
  "height": "178.0",
  "citizenship": "Spain",
  "is_eu": "True",
  "position": "Defender - Left-Back",
  "main_position": "Defender",
  "foot": "left",
  "current_club_id": "16022",
  "current_club_name": "Antequera CF",
  "joined": "2025-08-01",
  "contract_expires": "2026-06-30",
  "outfitter": "",
  "social_media_url": "http://www.instagram.com/antoniiioluna/",
  "player_agent_id": "7497",
  "player_agent_name": "KHA-Squared",
  "contract_option": "",
  "date_of_last_contract_extension": "",
  "on_loan_from_club_id": "",
  "on_loan_from_club_name": "",
  "contract_there_expires": "",
  "second_club_url": "",
  "second_club_name": "",
  "third_club_url": "",
  "third_club_name": "",
  "fourth_club_url": "",
  "fourth_club_name": "",
  "date_of_death": ""
}