{
  "player_id": "196860",
  "player_slug": "jordan-botaka",
  "player_name": "Jordan Botaka (196860)",
  "player_image_url": "https://img.a.transfermarkt.technology/portrait/header/196860-1630067270.jpg",
  "name_in_home_country": "Jordan Rolly Botaka",
  "date_of_birth": "1993-06-24",
  "place_of_birth": "Kinshasa",
  "country_of_birth": "DR Congo",
  "height": "184.0",
  "citizenship": "DR Congo  Netherlands",
  "is_eu": "True",
  "position": "Attack - Right Winger",
  "main_position": "Attack",
  "foot": "right",
  "current_club_id": "10666",
  "current_club_name": "Union Saint-Gilloise U23",
  "joined": "2025-09-06",
  "contract_expires": "",
  "outfitter": "",
  "social_media_url": "http://twitter.com/BotakaJordan",
  "player_agent_id": "4739",
  "player_agent_name": "Shahar Greenberg",
  "contract_option": "",
  "date_of_last_contract_extension": "",
  "on_loan_from_club_id": "",
  "on_loan_from_club_name": "",
  "contract_there_expires": "",
  "second_club_url": "",
  "second_club_name": "",
  "third_club_url": "",
  "third_club_name": "",
  "fourth_club_url": "",
  "fourth_club_name": "",
  "date_of_death": ""
}