{
  "player_id": "213851",
  "player_slug": "robin-simovic",
  "player_name": "Robin Simovic (213851)",
  "player_image_url": "https://img.a.transfermarkt.technology/portrait/header/213851-1446812812.jpg",
  "name_in_home_country": "Robin Simović",
  "date_of_birth": "1991-05-29",
  "place_of_birth": "Malmö",
  "country_of_birth": "Sweden",
  "height": "199.0",
  "citizenship": "Sweden",
  "is_eu": "True",
  "position": "Attack - Centre-Forward",
  "main_position": "Attack",
  "foot": "right",
  "current_club_id": "515",
  "current_club_name": "Without Club",
  "joined": "2024-07-01",
  "contract_expires": "",
  "outfitter": "",
  "social_media_url": "http://www.instagram.com/robinsimovic/",
  "player_agent_id": "4957",
  "player_agent_name": "Jonathan Chalkias",
  "contract_option": "",
  "date_of_last_contract_extension": "",
  "on_loan_from_club_id": "",
  "on_loan_from_club_name": "",
  "contract_there_expires": "",
  "second_club_url": "",
  "second_club_name": "",
  "third_club_url": "",
  "third_club_name": "",
  "fourth_club_url": "",
  "fourth_club_name": "",
  "date_of_death": ""
}