{
  "player_id": "232859",
  "player_slug": "cristian-benavente",
  "player_name": "Cristian Benavente (232859)",
  "player_image_url": "https://img.a.transfermarkt.technology/portrait/header/232859-1746513693.png",
  "name_in_home_country": "Cristian Benavente Bristol",
  "date_of_birth": "1994-05-19",
  "place_of_birth": "Alcalá de Henares",
  "country_of_birth": "Peru",
  "height": "172.0",
  "citizenship": "Peru  Spain",
  "is_eu": "True",
  "position": "Midfield - Attacking Midfield",
  "main_position": "Midfield",
  "foot": "both",
  "current_club_id": "1450",
  "current_club_name": "Club Sporting Cristal",
  "joined": "2025-08-08",
  "contract_expires": "2026-12-31",
  "outfitter": "Nike",
  "social_media_url": "http://twitter.com/CBBDix",
  "player_agent_id": "",
  "player_agent_name": "no agent",
  "contract_option": "",
  "date_of_last_contract_extension": "",
  "on_loan_from_club_id": "",
  "on_loan_from_club_name": "",
  "contract_there_expires": "",
  "second_club_url": "",
  "second_club_name": "",
  "third_club_url": "",
  "third_club_name": "",
  "fourth_club_url": "",
  "fourth_club_name": "",
  "date_of_death": ""
}