{
  "player_id": "347958",
  "player_slug": "gaetan-weissbeck",
  "player_name": "Gaétan Weissbeck (347958)",
  "player_image_url": "https://img.a.transfermarkt.technology/portrait/header/347958-1732282818.png",
  "name_in_home_country": "",
  "date_of_birth": "1997-01-17",
  "place_of_birth": "Wissembourg",
  "country_of_birth": "France",
  "height": "177.0",
  "citizenship": "France",
  "is_eu": "True",
  "position": "Midfield - Attacking Midfield",
  "main_position": "Midfield",
  "foot": "right",
  "current_club_id": "429",
  "current_club_name": "Apollon Limassol",
  "joined": "2024-08-13",
  "contract_expires": "2026-05-31",
  "outfitter": "",
  "social_media_url": "http://www.instagram.com/gw__28/",
  "player_agent_id": "1",
  "player_agent_name": "ROGON",
  "contract_option": "",
  "date_of_last_contract_extension": "",
  "on_loan_from_club_id": "",
  "on_loan_from_club_name": "",
  "contract_there_expires": "",
  "second_club_url": "",
  "second_club_name": "",
  "third_club_url": "",
  "third_club_name": "",
  "fourth_club_url": "",
  "fourth_club_name": "",
  "date_of_death": ""
}