{
  "player_id": "354912",
  "player_slug": "amadou-dia",
  "player_name": "Amadou Dia (354912)",
  "player_image_url": "https://img.a.transfermarkt.technology/portrait/header/354912-1685208590.jpg",
  "name_in_home_country": "Amadou Tidiane Dia",
  "date_of_birth": "1993-06-08",
  "place_of_birth": "Nantes",
  "country_of_birth": "United States",
  "height": "177.0",
  "citizenship": "United States  France",
  "is_eu": "True",
  "position": "Defender - Left-Back",
  "main_position": "Defender",
  "foot": "",
  "current_club_id": "46316",
  "current_club_name": "Louisville City FC",
  "joined": "2022-01-14",
  "contract_expires": "2025-11-30",
  "outfitter": "",
  "social_media_url": "http://twitter.com/Amadou_iT11",
  "player_agent_id": "5638",
  "player_agent_name": "NOVERA Sports",
  "contract_option": "",
  "date_of_last_contract_extension": "2024-07-17",
  "on_loan_from_club_id": "",
  "on_loan_from_club_name": "",
  "contract_there_expires": "",
  "second_club_url": "",
  "second_club_name": "",
  "third_club_url": "",
  "third_club_name": "",
  "fourth_club_url": "",
  "fourth_club_name": "",
  "date_of_death": ""
}