{
  "player_id": "424784",
  "player_slug": "luis-suarez",
  "player_name": "Luis Suárez (424784)",
  "player_image_url": "https://img.a.transfermarkt.technology/portrait/header/424784-1732735655.jpg",
  "name_in_home_country": "Luis Javier Suárez Charris",
  "date_of_birth": "1997-12-02",
  "place_of_birth": "Santa Marta",
  "country_of_birth": "Colombia",
  "height": "181.0",
  "citizenship": "Colombia  Spain",
  "is_eu": "True",
  "position": "Attack - Centre-Forward",
  "main_position": "Attack",
  "foot": "right",
  "current_club_id": "336",
  "current_club_name": "Sporting CP",
  "joined": "2025-07-28",
  "contract_expires": "2030-06-30",
  "outfitter": "adidas",
  "social_media_url": "http://www.instagram.com/luissuarez.26/",
  "player_agent_id": "13",
  "player_agent_name": "LIAN Sports Group",
  "contract_option": "",
  "date_of_last_contract_extension": "",
  "on_loan_from_club_id": "",
  "on_loan_from_club_name": "",
  "contract_there_expires": "",
  "second_club_url": "",
  "second_club_name": "",
  "third_club_url": "",
  "third_club_name": "",
  "fourth_club_url": "",
  "fourth_club_name": "",
  "date_of_death": ""
}