{
  "player_id": "461654",
  "player_slug": "taras-dmytruk",
  "player_name": "Taras Dmytruk (461654)",
  "player_image_url": "https://img.a.transfermarkt.technology/portrait/header/461654-1611776134.png",
  "name_in_home_country": "Дмитрук Тарас Валерійович",
  "date_of_birth": "2000-03-09",
  "place_of_birth": "Novovolynsk, Volyn Oblast",
  "country_of_birth": "Ukraine",
  "height": "171.0",
  "citizenship": "Ukraine",
  "is_eu": "False",
  "position": "Defender - Right-Back",
  "main_position": "Defender",
  "foot": "right",
  "current_club_id": "2740",
  "current_club_name": "Vorskla Poltava",
  "joined": "2025-07-30",
  "contract_expires": "2026-06-30",
  "outfitter": "",
  "social_media_url": "",
  "player_agent_id": "3703",
  "player_agent_name": "ProStar",
  "contract_option": "",
  "date_of_last_contract_extension": "",
  "on_loan_from_club_id": "",
  "on_loan_from_club_name": "",
  "contract_there_expires": "",
  "second_club_url": "",
  "second_club_name": "",
  "third_club_url": "",
  "third_club_name": "",
  "fourth_club_url": "",
  "fourth_club_name": "",
  "date_of_death": ""
}