{
  "player_id": "489871",
  "player_slug": "marko-kelemen",
  "player_name": "Marko Kelemen (489871)",
  "player_image_url": "https://img.a.transfermarkt.technology/portrait/header/489871-1584677320.png",
  "name_in_home_country": "",
  "date_of_birth": "2000-04-29",
  "place_of_birth": "Rožňava",
  "country_of_birth": "Slovakia",
  "height": "188.0",
  "citizenship": "Slovakia",
  "is_eu": "True",
  "position": "Attack - Centre-Forward",
  "main_position": "Attack",
  "foot": "right",
  "current_club_id": "7087",
  "current_club_name": "MFK Ruzomberok",
  "joined": "2022-07-01",
  "contract_expires": "2026-05-31",
  "outfitter": "",
  "social_media_url": "",
  "player_agent_id": "4475",
  "player_agent_name": "AM-PRO Players ...",
  "contract_option": "",
  "date_of_last_contract_extension": "",
  "on_loan_from_club_id": "",
  "on_loan_from_club_name": "",
  "contract_there_expires": "",
  "second_club_url": "",
  "second_club_name": "",
  "third_club_url": "",
  "third_club_name": "",
  "fourth_club_url": "",
  "fourth_club_name": "",
  "date_of_death": ""
}