{
  "player_id": "564544",
  "player_slug": "pedro-amador",
  "player_name": "Pedro Amador (564544)",
  "player_image_url": "https://img.a.transfermarkt.technology/portrait/header/564544-1740822585.jpg",
  "name_in_home_country": "Pedro Miguel Santos Amador",
  "date_of_birth": "1998-12-18",
  "place_of_birth": "Loures",
  "country_of_birth": "Portugal",
  "height": "181.0",
  "citizenship": "Portugal",
  "is_eu": "True",
  "position": "Defender - Left-Back",
  "main_position": "Defender",
  "foot": "left",
  "current_club_id": "51663",
  "current_club_name": "Atlanta United FC",
  "joined": "2024-07-18",
  "contract_expires": "2026-12-31",
  "outfitter": "",
  "social_media_url": "http://www.instagram.com/pedroamador18/",
  "player_agent_id": "2146",
  "player_agent_name": "InterStarDeporte",
  "contract_option": "club option 1 year",
  "date_of_last_contract_extension": "",
  "on_loan_from_club_id": "",
  "on_loan_from_club_name": "",
  "contract_there_expires": "",
  "second_club_url": "",
  "second_club_name": "",
  "third_club_url": "",
  "third_club_name": "",
  "fourth_club_url": "",
  "fourth_club_name": "",
  "date_of_death": ""
}