{
  "player_id": "575610",
  "player_slug": "thibault-klidje",
  "player_name": "Thibault Klidjé (575610)",
  "player_image_url": "https://img.a.transfermarkt.technology/portrait/header/575610-1746171398.png",
  "name_in_home_country": "",
  "date_of_birth": "2001-07-10",
  "place_of_birth": "Hahotoe",
  "country_of_birth": "Togo",
  "height": "170.0",
  "citizenship": "Togo",
  "is_eu": "False",
  "position": "Attack - Centre-Forward",
  "main_position": "Attack",
  "foot": "right",
  "current_club_id": "903",
  "current_club_name": "Hibernian FC",
  "joined": "2025-07-13",
  "contract_expires": "2028-06-30",
  "outfitter": "",
  "social_media_url": "",
  "player_agent_id": "10594",
  "player_agent_name": "BY Sport Consulting",
  "contract_option": "",
  "date_of_last_contract_extension": "",
  "on_loan_from_club_id": "",
  "on_loan_from_club_name": "",
  "contract_there_expires": "",
  "second_club_url": "",
  "second_club_name": "",
  "third_club_url": "",
  "third_club_name": "",
  "fourth_club_url": "",
  "fourth_club_name": "",
  "date_of_death": ""
}