{
  "player_id": "604568",
  "player_slug": "elias-rahn",
  "player_name": "Elias Rahn (604568)",
  "player_image_url": "https://img.a.transfermarkt.technology/portrait/header/604568-1629054337.jpg",
  "name_in_home_country": "Jan Elias Rahn",
  "date_of_birth": "2002-07-16",
  "place_of_birth": "Stuttgart",
  "country_of_birth": "Germany",
  "height": "175.0",
  "citizenship": "Germany",
  "is_eu": "True",
  "position": "Defender - Right-Back",
  "main_position": "Defender",
  "foot": "both",
  "current_club_id": "2589",
  "current_club_name": "SG Sonnenhof Großaspach",
  "joined": "2021-07-01",
  "contract_expires": "2027-06-30",
  "outfitter": "",
  "social_media_url": "",
  "player_agent_id": "1478",
  "player_agent_name": "Heiko T. Weber",
  "contract_option": "",
  "date_of_last_contract_extension": "2025-05-21",
  "on_loan_from_club_id": "",
  "on_loan_from_club_name": "",
  "contract_there_expires": "",
  "second_club_url": "",
  "second_club_name": "",
  "third_club_url": "",
  "third_club_name": "",
  "fourth_club_url": "",
  "fourth_club_name": "",
  "date_of_death": ""
}