{
  "player_id": "617443",
  "player_slug": "juan-silva",
  "player_name": "Juan Silva (617443)",
  "player_image_url": "https://img.a.transfermarkt.technology/portrait/header/617443-1700682334.jpg",
  "name_in_home_country": "Juan Ignacio Pajín Silva",
  "date_of_birth": "1998-08-02",
  "place_of_birth": "Mar del Plata",
  "country_of_birth": "Argentina",
  "height": "183.0",
  "citizenship": "Argentina  Spain",
  "is_eu": "True",
  "position": "Defender - Right-Back",
  "main_position": "Defender",
  "foot": "right",
  "current_club_id": "33306",
  "current_club_name": "Gimnástica Segoviana CF",
  "joined": "2023-08-03",
  "contract_expires": "2026-06-30",
  "outfitter": "",
  "social_media_url": "",
  "player_agent_id": "6776",
  "player_agent_name": "Oceans Sport",
  "contract_option": "",
  "date_of_last_contract_extension": "",
  "on_loan_from_club_id": "",
  "on_loan_from_club_name": "",
  "contract_there_expires": "",
  "second_club_url": "",
  "second_club_name": "",
  "third_club_url": "",
  "third_club_name": "",
  "fourth_club_url": "",
  "fourth_club_name": "",
  "date_of_death": ""
}