{
  "player_id": "863619",
  "player_slug": "ozzie-ramos",
  "player_name": "Ozzie Ramos (863619)",
  "player_image_url": "https://img.a.transfermarkt.technology/portrait/header/863619-1681496886.jpg",
  "name_in_home_country": "",
  "date_of_birth": "1996-09-11",
  "place_of_birth": "Modesto, California",
  "country_of_birth": "United States",
  "height": "178.0",
  "citizenship": "United States  Mexico",
  "is_eu": "False",
  "position": "Midfield - Central Midfield",
  "main_position": "Midfield",
  "foot": "left",
  "current_club_id": "115284",
  "current_club_name": "Texoma FC",
  "joined": "2025-03-11",
  "contract_expires": "2025-11-30",
  "outfitter": "",
  "social_media_url": "http://twitter.com/ozzie__ramos",
  "player_agent_id": "8124",
  "player_agent_name": "Tavares Agency LLC",
  "contract_option": "",
  "date_of_last_contract_extension": "",
  "on_loan_from_club_id": "",
  "on_loan_from_club_name": "",
  "contract_there_expires": "",
  "second_club_url": "",
  "second_club_name": "",
  "third_club_url": "",
  "third_club_name": "",
  "fourth_club_url": "",
  "fourth_club_name": "",
  "date_of_death": ""
}