{
  "player_id": "99548",
  "player_slug": "douglas",
  "player_name": "Douglas (99548)",
  "player_image_url": "https://img.a.transfermarkt.technology/portrait/header/99548-1628111699.jpg",
  "name_in_home_country": "Dyanfres Douglas Chagas Matos",
  "date_of_birth": "1987-12-30",
  "place_of_birth": "Morros",
  "country_of_birth": "Brazil",
  "height": "184.0",
  "citizenship": "Brazil",
  "is_eu": "False",
  "position": "Attack - Centre-Forward",
  "main_position": "Attack",
  "foot": "left",
  "current_club_id": "123",
  "current_club_name": "Retired",
  "joined": "2024-02-15",
  "contract_expires": "",
  "outfitter": "",
  "social_media_url": "http://www.instagram.com/dyandouglas49/",
  "player_agent_id": "780",
  "player_agent_name": "Brazil Soccer",
  "contract_option": "",
  "date_of_last_contract_extension": "",
  "on_loan_from_club_id": "",
  "on_loan_from_club_name": "",
  "contract_there_expires": "",
  "second_club_url": "",
  "second_club_name": "",
  "third_club_url": "",
  "third_club_name": "",
  "fourth_club_url": "",
  "fourth_club_name": "",
  "date_of_death": ""
}